{
  "id": 951048,
  "title": "The Human Surge 3",
  "original_title": "El auge del humano 3",
  "release_date": "2024-07-03",
  "status": "Released",
  "runtime": 121,
  "original_language": "es",
  "spoken_languages": [
    {
      "english_name": "Mandarin",
      "iso_639_1": "zh",
      "name": "\u666e\u901a\u8bdd"
    },
    {
      "english_name": "English",
      "iso_639_1": "en",
      "name": "English"
    },
    {
      "english_name": "Spanish",
      "iso_639_1": "es",
      "name": "Espa\u00f1ol"
    },
    {
      "english_name": "Sinhalese",
      "iso_639_1": "si",
      "name": "\u0dc3\u0dd2\u0d82\u0dc4\u0dbd"
    },
    {
      "english_name": "Tamil",
      "iso_639_1": "ta",
      "name": "\u0ba4\u0bae\u0bbf\u0bb4\u0bcd"
    }
  ],
  "origin_country": [
    "AR",
    "BR",
    "HK",
    "NL",
    "PE",
    "PT",
    "LK",
    "TW"
  ],
  "genres": [
    {
      "id": 18,
      "name": "Drama"
    }
  ]
}