{
  "id": 54898,
  "title": "The Green Ray",
  "original_title": "Le Rayon vert",
  "release_date": "1986-08-29",
  "status": "Released",
  "runtime": 99,
  "original_language": "fr",
  "spoken_languages": [
    {
      "english_name": "English",
      "iso_639_1": "en",
      "name": "English"
    },
    {
      "english_name": "French",
      "iso_639_1": "fr",
      "name": "Fran\u00e7ais"
    },
    {
      "english_name": "Spanish",
      "iso_639_1": "es",
      "name": "Espa\u00f1ol"
    },
    {
      "english_name": "German",
      "iso_639_1": "de",
      "name": "Deutsch"
    }
  ],
  "origin_country": [
    "FR"
  ],
  "genres": [
    {
      "id": 18,
      "name": "Drama"
    },
    {
      "id": 10749,
      "name": "Romance"
    }
  ]
}