{
  "id": 42602,
  "title": "The Passion of Anna",
  "original_title": "En passion",
  "release_date": "1969-11-10",
  "status": "Released",
  "runtime": 101,
  "original_language": "sv",
  "spoken_languages": [
    {
      "english_name": "German",
      "iso_639_1": "de",
      "name": "Deutsch"
    },
    {
      "english_name": "Swedish",
      "iso_639_1": "sv",
      "name": "svenska"
    }
  ],
  "origin_country": [
    "SE"
  ],
  "genres": [
    {
      "id": 18,
      "name": "Drama"
    }
  ]
}