{
  "id": 91892,
  "title": "Hokuriku Proxy War",
  "original_title": "\u5317\u9678\u4ee3\u7406\u6226\u4e89",
  "release_date": "1977-02-26",
  "status": "Released",
  "runtime": 98,
  "original_language": "ja",
  "spoken_languages": [
    {
      "english_name": "Japanese",
      "iso_639_1": "ja",
      "name": "\u65e5\u672c\u8a9e"
    }
  ],
  "origin_country": [
    "JP"
  ],
  "genres": [
    {
      "id": 18,
      "name": "Drama"
    },
    {
      "id": 80,
      "name": "Crime"
    },
    {
      "id": 28,
      "name": "Action"
    },
    {
      "id": 35,
      "name": "Comedy"
    }
  ]
}