{
  "id": 70590,
  "title": "Singham",
  "original_title": "Singham",
  "release_date": "2011-07-22",
  "status": "Released",
  "runtime": 143,
  "original_language": "hi",
  "spoken_languages": [
    {
      "english_name": "English",
      "iso_639_1": "en",
      "name": "English"
    },
    {
      "english_name": "Gujarati",
      "iso_639_1": "gu",
      "name": ""
    },
    {
      "english_name": "Hindi",
      "iso_639_1": "hi",
      "name": "\u0939\u093f\u0928\u094d\u0926\u0940"
    },
    {
      "english_name": "Marathi",
      "iso_639_1": "mr",
      "name": ""
    }
  ],
  "origin_country": [
    "IN"
  ],
  "genres": [
    {
      "id": 18,
      "name": "Drama"
    },
    {
      "id": 28,
      "name": "Action"
    },
    {
      "id": 80,
      "name": "Crime"
    }
  ]
}