{
  "id": 453127,
  "title": "Midnight Runners",
  "original_title": "\uccad\ub144\uacbd\ucc30",
  "release_date": "2017-08-09",
  "status": "Released",
  "runtime": 109,
  "original_language": "ko",
  "spoken_languages": [
    {
      "english_name": "Korean",
      "iso_639_1": "ko",
      "name": "\ud55c\uad6d\uc5b4/\uc870\uc120\ub9d0"
    }
  ],
  "origin_country": [
    "KR"
  ],
  "genres": [
    {
      "id": 35,
      "name": "Comedy"
    },
    {
      "id": 28,
      "name": "Action"
    },
    {
      "id": 80,
      "name": "Crime"
    }
  ]
}