{
  "id": 97527,
  "title": "The Girl in Room 2A",
  "original_title": "La casa della paura",
  "release_date": "1974-07-01",
  "status": "Released",
  "runtime": 90,
  "original_language": "it",
  "spoken_languages": [
    {
      "english_name": "Italian",
      "iso_639_1": "it",
      "name": "Italiano"
    }
  ],
  "origin_country": [
    "IT"
  ],
  "genres": [
    {
      "id": 27,
      "name": "Horror"
    },
    {
      "id": 53,
      "name": "Thriller"
    },
    {
      "id": 80,
      "name": "Crime"
    },
    {
      "id": 9648,
      "name": "Mystery"
    }
  ]
}