{
  "id": 26162,
  "title": "The Bat Whispers",
  "original_title": "The Bat Whispers",
  "release_date": "1930-11-13",
  "status": "Released",
  "runtime": 83,
  "original_language": "en",
  "spoken_languages": [
    {
      "english_name": "English",
      "iso_639_1": "en",
      "name": "English"
    }
  ],
  "origin_country": [
    "US"
  ],
  "genres": [
    {
      "id": 9648,
      "name": "Mystery"
    },
    {
      "id": 35,
      "name": "Comedy"
    },
    {
      "id": 80,
      "name": "Crime"
    },
    {
      "id": 27,
      "name": "Horror"
    }
  ]
}