{
  "id": 2687,
  "title": "Memoirs of an Invisible Man",
  "original_title": "Memoirs of an Invisible Man",
  "release_date": "1992-02-28",
  "status": "Released",
  "runtime": 99,
  "original_language": "en",
  "spoken_languages": [
    {
      "english_name": "English",
      "iso_639_1": "en",
      "name": "English"
    }
  ],
  "origin_country": [
    "US"
  ],
  "genres": [
    {
      "id": 878,
      "name": "Science Fiction"
    },
    {
      "id": 35,
      "name": "Comedy"
    },
    {
      "id": 10749,
      "name": "Romance"
    },
    {
      "id": 53,
      "name": "Thriller"
    }
  ]
}