{
  "id": 381696,
  "title": "Shrek the Musical",
  "original_title": "Shrek the Musical",
  "release_date": "2013-09-17",
  "status": "Released",
  "runtime": 130,
  "original_language": "en",
  "spoken_languages": [
    {
      "english_name": "English",
      "iso_639_1": "en",
      "name": "English"
    }
  ],
  "origin_country": [
    "US"
  ],
  "genres": [
    {
      "id": 10402,
      "name": "Music"
    },
    {
      "id": 35,
      "name": "Comedy"
    },
    {
      "id": 14,
      "name": "Fantasy"
    }
  ]
}