{
  "id": 17685,
  "title": "King of Hearts",
  "original_title": "Le Roi de c\u0153ur",
  "release_date": "1966-12-21",
  "status": "Released",
  "runtime": 102,
  "original_language": "fr",
  "spoken_languages": [
    {
      "english_name": "German",
      "iso_639_1": "de",
      "name": "Deutsch"
    },
    {
      "english_name": "French",
      "iso_639_1": "fr",
      "name": "Fran\u00e7ais"
    },
    {
      "english_name": "English",
      "iso_639_1": "en",
      "name": "English"
    }
  ],
  "origin_country": [
    "FR"
  ],
  "genres": [
    {
      "id": 35,
      "name": "Comedy"
    },
    {
      "id": 18,
      "name": "Drama"
    },
    {
      "id": 10752,
      "name": "War"
    }
  ]
}