{
  "id": 179,
  "title": "The Interpreter",
  "original_title": "The Interpreter",
  "release_date": "2005-04-08",
  "status": "Released",
  "runtime": 128,
  "original_language": "en",
  "spoken_languages": [
    {
      "english_name": "French",
      "iso_639_1": "fr",
      "name": "Fran\u00e7ais"
    },
    {
      "english_name": "English",
      "iso_639_1": "en",
      "name": "English"
    },
    {
      "english_name": "Portuguese",
      "iso_639_1": "pt",
      "name": "Portugu\u00eas"
    }
  ],
  "origin_country": [
    "US",
    "GB"
  ],
  "genres": [
    {
      "id": 80,
      "name": "Crime"
    },
    {
      "id": 53,
      "name": "Thriller"
    }
  ]
}