{
  "id": 43028,
  "title": "Victim",
  "original_title": "Victim",
  "release_date": "1961-08-01",
  "status": "Released",
  "runtime": 96,
  "original_language": "en",
  "spoken_languages": [
    {
      "english_name": "English",
      "iso_639_1": "en",
      "name": "English"
    }
  ],
  "origin_country": [
    "GB"
  ],
  "genres": [
    {
      "id": 18,
      "name": "Drama"
    },
    {
      "id": 80,
      "name": "Crime"
    },
    {
      "id": 53,
      "name": "Thriller"
    }
  ]
}