{
  "id": 437342,
  "title": "The First Omen",
  "original_title": "The First Omen",
  "release_date": "2024-04-03",
  "status": "Released",
  "runtime": 119,
  "original_language": "en",
  "spoken_languages": [
    {
      "english_name": "English",
      "iso_639_1": "en",
      "name": "English"
    },
    {
      "english_name": "Italian",
      "iso_639_1": "it",
      "name": "Italiano"
    }
  ],
  "origin_country": [
    "US"
  ],
  "genres": [
    {
      "id": 27,
      "name": "Horror"
    }
  ]
}