{
  "id": 239030,
  "title": "Love Steaks",
  "original_title": "Love Steaks",
  "release_date": "2014-03-27",
  "status": "Released",
  "runtime": 89,
  "original_language": "de",
  "spoken_languages": [
    {
      "english_name": "German",
      "iso_639_1": "de",
      "name": "Deutsch"
    }
  ],
  "origin_country": [
    "DE"
  ],
  "genres": [
    {
      "id": 35,
      "name": "Comedy"
    },
    {
      "id": 18,
      "name": "Drama"
    },
    {
      "id": 10749,
      "name": "Romance"
    }
  ]
}