{
  "id": 28218,
  "title": "Deathstalker II: Duel of the Titans",
  "original_title": "Deathstalker II: Duel of the Titans",
  "release_date": "1987-06-03",
  "status": "Released",
  "runtime": 77,
  "original_language": "en",
  "spoken_languages": [
    {
      "english_name": "English",
      "iso_639_1": "en",
      "name": "English"
    }
  ],
  "origin_country": [
    "US"
  ],
  "genres": [
    {
      "id": 28,
      "name": "Action"
    },
    {
      "id": 12,
      "name": "Adventure"
    },
    {
      "id": 35,
      "name": "Comedy"
    },
    {
      "id": 14,
      "name": "Fantasy"
    }
  ]
}