{
  "id": 28295,
  "title": "I Saw What You Did",
  "original_title": "I Saw What You Did",
  "release_date": "1965-07-21",
  "status": "Released",
  "runtime": 82,
  "original_language": "en",
  "spoken_languages": [
    {
      "english_name": "English",
      "iso_639_1": "en",
      "name": "English"
    }
  ],
  "origin_country": [
    "US"
  ],
  "genres": [
    {
      "id": 53,
      "name": "Thriller"
    },
    {
      "id": 27,
      "name": "Horror"
    },
    {
      "id": 80,
      "name": "Crime"
    }
  ]
}