{
  "id": 29266,
  "title": "War and Peace",
  "original_title": "\u0412\u043e\u0439\u043d\u0430 \u0438 \u043c\u0438\u0440",
  "release_date": "1967-11-04",
  "status": "Released",
  "runtime": 422,
  "original_language": "ru",
  "spoken_languages": [
    {
      "english_name": "German",
      "iso_639_1": "de",
      "name": "Deutsch"
    },
    {
      "english_name": "French",
      "iso_639_1": "fr",
      "name": "Fran\u00e7ais"
    },
    {
      "english_name": "Hungarian",
      "iso_639_1": "hu",
      "name": "Magyar"
    },
    {
      "english_name": "Russian",
      "iso_639_1": "ru",
      "name": "P\u0443\u0441\u0441\u043a\u0438\u0439"
    }
  ],
  "origin_country": [
    "SU"
  ],
  "genres": [
    {
      "id": 36,
      "name": "History"
    },
    {
      "id": 18,
      "name": "Drama"
    },
    {
      "id": 10752,
      "name": "War"
    },
    {
      "id": 10749,
      "name": "Romance"
    }
  ]
}