{
  "id": 296917,
  "title": "PSYCHO-PASS: The Movie",
  "original_title": "\u5287\u5834\u7248 PSYCHO-PASS \u30b5\u30a4\u30b3\u30d1\u30b9",
  "release_date": "2015-01-09",
  "status": "Released",
  "runtime": 113,
  "original_language": "ja",
  "spoken_languages": [
    {
      "english_name": "Japanese",
      "iso_639_1": "ja",
      "name": "\u65e5\u672c\u8a9e"
    }
  ],
  "origin_country": [
    "JP"
  ],
  "genres": [
    {
      "id": 16,
      "name": "Animation"
    },
    {
      "id": 878,
      "name": "Science Fiction"
    },
    {
      "id": 28,
      "name": "Action"
    }
  ]
}