{
  "id": 58402,
  "title": "The Boss",
  "original_title": "Il boss",
  "release_date": "1973-02-01",
  "status": "Released",
  "runtime": 109,
  "original_language": "it",
  "spoken_languages": [
    {
      "english_name": "Italian",
      "iso_639_1": "it",
      "name": "Italiano"
    }
  ],
  "origin_country": [
    "IT"
  ],
  "genres": [
    {
      "id": 80,
      "name": "Crime"
    },
    {
      "id": 28,
      "name": "Action"
    },
    {
      "id": 53,
      "name": "Thriller"
    }
  ]
}