{
  "id": 31067,
  "title": "Fail Safe",
  "original_title": "Fail Safe",
  "release_date": "2000-04-09",
  "status": "Released",
  "runtime": 86,
  "original_language": "en",
  "spoken_languages": [
    {
      "english_name": "English",
      "iso_639_1": "en",
      "name": "English"
    }
  ],
  "origin_country": [
    "US"
  ],
  "genres": [
    {
      "id": 18,
      "name": "Drama"
    },
    {
      "id": 53,
      "name": "Thriller"
    },
    {
      "id": 10770,
      "name": "TV Movie"
    }
  ]
}