{
  "id": 845781,
  "title": "Red One",
  "original_title": "Red One",
  "release_date": "2024-10-31",
  "status": "Released",
  "runtime": 124,
  "original_language": "en",
  "spoken_languages": [
    {
      "english_name": "English",
      "iso_639_1": "en",
      "name": "English"
    }
  ],
  "origin_country": [
    "US"
  ],
  "genres": [
    {
      "id": 28,
      "name": "Action"
    },
    {
      "id": 35,
      "name": "Comedy"
    },
    {
      "id": 14,
      "name": "Fantasy"
    }
  ]
}