{
  "id": 1150521,
  "title": "Christmas on Windmill Way",
  "original_title": "Christmas on Windmill Way",
  "release_date": "2023-12-02",
  "status": "Released",
  "runtime": 84,
  "original_language": "en",
  "spoken_languages": [
    {
      "english_name": "English",
      "iso_639_1": "en",
      "name": "English"
    }
  ],
  "origin_country": [
    "US"
  ],
  "genres": [
    {
      "id": 10749,
      "name": "Romance"
    },
    {
      "id": 35,
      "name": "Comedy"
    },
    {
      "id": 10770,
      "name": "TV Movie"
    }
  ]
}