{
  "id": 116745,
  "title": "The Secret Life of Walter Mitty",
  "original_title": "The Secret Life of Walter Mitty",
  "release_date": "2013-12-18",
  "status": "Released",
  "runtime": 114,
  "original_language": "en",
  "spoken_languages": [
    {
      "english_name": "English",
      "iso_639_1": "en",
      "name": "English"
    },
    {
      "english_name": "Icelandic",
      "iso_639_1": "is",
      "name": "\u00cdslenska"
    },
    {
      "english_name": "Spanish",
      "iso_639_1": "es",
      "name": "Espa\u00f1ol"
    }
  ],
  "origin_country": [
    "US"
  ],
  "genres": [
    {
      "id": 12,
      "name": "Adventure"
    },
    {
      "id": 35,
      "name": "Comedy"
    },
    {
      "id": 18,
      "name": "Drama"
    },
    {
      "id": 14,
      "name": "Fantasy"
    }
  ]
}