{
  "id": 20771,
  "title": "Kim Possible Movie: So the Drama",
  "original_title": "Kim Possible Movie: So the Drama",
  "release_date": "2005-04-08",
  "status": "Released",
  "runtime": 71,
  "original_language": "en",
  "spoken_languages": [
    {
      "english_name": "English",
      "iso_639_1": "en",
      "name": "English"
    }
  ],
  "origin_country": [
    "US"
  ],
  "genres": [
    {
      "id": 16,
      "name": "Animation"
    },
    {
      "id": 12,
      "name": "Adventure"
    },
    {
      "id": 10751,
      "name": "Family"
    },
    {
      "id": 28,
      "name": "Action"
    },
    {
      "id": 35,
      "name": "Comedy"
    },
    {
      "id": 878,
      "name": "Science Fiction"
    }
  ]
}