{
  "id": 1371202,
  "title": "iHostage",
  "original_title": "iHostage",
  "release_date": "2025-04-18",
  "status": "Released",
  "runtime": 100,
  "original_language": "nl",
  "spoken_languages": [
    {
      "english_name": "Dutch",
      "iso_639_1": "nl",
      "name": "Nederlands"
    },
    {
      "english_name": "English",
      "iso_639_1": "en",
      "name": "English"
    }
  ],
  "origin_country": [
    "NL"
  ],
  "genres": [
    {
      "id": 53,
      "name": "Thriller"
    },
    {
      "id": 80,
      "name": "Crime"
    },
    {
      "id": 18,
      "name": "Drama"
    }
  ]
}