{
  "id": 570670,
  "title": "The Invisible Man",
  "original_title": "The Invisible Man",
  "release_date": "2020-02-26",
  "status": "Released",
  "runtime": 124,
  "original_language": "en",
  "spoken_languages": [
    {
      "english_name": "English",
      "iso_639_1": "en",
      "name": "English"
    }
  ],
  "origin_country": [
    "AU",
    "US"
  ],
  "genres": [
    {
      "id": 53,
      "name": "Thriller"
    },
    {
      "id": 878,
      "name": "Science Fiction"
    },
    {
      "id": 27,
      "name": "Horror"
    }
  ]
}