{
  "id": 50512,
  "title": "Anna Karenina",
  "original_title": "Anna Karenina",
  "release_date": "1997-04-04",
  "status": "Released",
  "runtime": 108,
  "original_language": "en",
  "spoken_languages": [
    {
      "english_name": "English",
      "iso_639_1": "en",
      "name": "English"
    },
    {
      "english_name": "Russian",
      "iso_639_1": "ru",
      "name": "P\u0443\u0441\u0441\u043a\u0438\u0439"
    }
  ],
  "origin_country": [
    "RU",
    "GB",
    "US"
  ],
  "genres": [
    {
      "id": 18,
      "name": "Drama"
    },
    {
      "id": 10749,
      "name": "Romance"
    }
  ]
}