{
  "id": 37530,
  "title": "House II: The Second Story",
  "original_title": "House II: The Second Story",
  "release_date": "1987-05-14",
  "status": "Released",
  "runtime": 88,
  "original_language": "en",
  "spoken_languages": [
    {
      "english_name": "English",
      "iso_639_1": "en",
      "name": "English"
    }
  ],
  "origin_country": [
    "US"
  ],
  "genres": [
    {
      "id": 14,
      "name": "Fantasy"
    },
    {
      "id": 27,
      "name": "Horror"
    },
    {
      "id": 35,
      "name": "Comedy"
    }
  ]
}