{
  "id": 376134,
  "title": "The Discovery",
  "original_title": "The Discovery",
  "release_date": "2017-03-31",
  "status": "Released",
  "runtime": 102,
  "original_language": "en",
  "spoken_languages": [
    {
      "english_name": "English",
      "iso_639_1": "en",
      "name": "English"
    }
  ],
  "origin_country": [
    "US"
  ],
  "genres": [
    {
      "id": 18,
      "name": "Drama"
    },
    {
      "id": 10749,
      "name": "Romance"
    },
    {
      "id": 878,
      "name": "Science Fiction"
    },
    {
      "id": 53,
      "name": "Thriller"
    },
    {
      "id": 9648,
      "name": "Mystery"
    }
  ]
}