{
  "id": 644089,
  "title": "Blue Bayou",
  "original_title": "Blue Bayou",
  "release_date": "2021-09-10",
  "status": "Released",
  "runtime": 117,
  "original_language": "en",
  "spoken_languages": [
    {
      "english_name": "English",
      "iso_639_1": "en",
      "name": "English"
    },
    {
      "english_name": "Korean",
      "iso_639_1": "ko",
      "name": "\ud55c\uad6d\uc5b4/\uc870\uc120\ub9d0"
    },
    {
      "english_name": "Vietnamese",
      "iso_639_1": "vi",
      "name": "Ti\u1ebfng Vi\u1ec7t"
    }
  ],
  "origin_country": [
    "CA",
    "US"
  ],
  "genres": [
    {
      "id": 18,
      "name": "Drama"
    }
  ]
}