{
  "id": 39376,
  "title": "Tales from the Golden Age",
  "original_title": "Amintiri din epoca de aur",
  "release_date": "2009-05-29",
  "status": "Released",
  "runtime": 155,
  "original_language": "ro",
  "spoken_languages": [
    {
      "english_name": "Romanian",
      "iso_639_1": "ro",
      "name": "Rom\u00e2n\u0103"
    }
  ],
  "origin_country": [
    "FR",
    "RO"
  ],
  "genres": [
    {
      "id": 35,
      "name": "Comedy"
    },
    {
      "id": 36,
      "name": "History"
    }
  ]
}