{
  "id": 6521,
  "title": "The Contender",
  "original_title": "The Contender",
  "release_date": "2000-10-13",
  "status": "Released",
  "runtime": 126,
  "original_language": "en",
  "spoken_languages": [
    {
      "english_name": "English",
      "iso_639_1": "en",
      "name": "English"
    },
    {
      "english_name": "German",
      "iso_639_1": "de",
      "name": "Deutsch"
    }
  ],
  "origin_country": [
    "US",
    "GB"
  ],
  "genres": [
    {
      "id": 18,
      "name": "Drama"
    },
    {
      "id": 53,
      "name": "Thriller"
    }
  ]
}