{
  "id": 779782,
  "title": "The School for Good and Evil",
  "original_title": "The School for Good and Evil",
  "release_date": "2022-10-19",
  "status": "Released",
  "runtime": 149,
  "original_language": "en",
  "spoken_languages": [
    {
      "english_name": "English",
      "iso_639_1": "en",
      "name": "English"
    },
    {
      "english_name": "German",
      "iso_639_1": "de",
      "name": "Deutsch"
    },
    {
      "english_name": "French",
      "iso_639_1": "fr",
      "name": "Fran\u00e7ais"
    }
  ],
  "origin_country": [
    "US"
  ],
  "genres": [
    {
      "id": 14,
      "name": "Fantasy"
    },
    {
      "id": 35,
      "name": "Comedy"
    },
    {
      "id": 12,
      "name": "Adventure"
    },
    {
      "id": 18,
      "name": "Drama"
    }
  ]
}