{
  "id": 10242,
  "title": "What Ever Happened to Baby Jane?",
  "original_title": "What Ever Happened to Baby Jane?",
  "release_date": "1962-10-31",
  "status": "Released",
  "runtime": 135,
  "original_language": "en",
  "spoken_languages": [
    {
      "english_name": "English",
      "iso_639_1": "en",
      "name": "English"
    }
  ],
  "origin_country": [
    "US"
  ],
  "genres": [
    {
      "id": 18,
      "name": "Drama"
    },
    {
      "id": 27,
      "name": "Horror"
    },
    {
      "id": 53,
      "name": "Thriller"
    }
  ]
}