{
  "id": 10593,
  "title": "The Phantom of the Opera",
  "original_title": "Il fantasma dell'Opera",
  "release_date": "1998-11-20",
  "status": "Released",
  "runtime": 104,
  "original_language": "it",
  "spoken_languages": [
    {
      "english_name": "English",
      "iso_639_1": "en",
      "name": "English"
    },
    {
      "english_name": "Italian",
      "iso_639_1": "it",
      "name": "Italiano"
    }
  ],
  "origin_country": [
    "IT"
  ],
  "genres": [
    {
      "id": 27,
      "name": "Horror"
    },
    {
      "id": 10749,
      "name": "Romance"
    },
    {
      "id": 9648,
      "name": "Mystery"
    }
  ]
}