{
  "id": 106904,
  "title": "The Bat Woman",
  "original_title": "La mujer murci\u00e9lago",
  "release_date": "1968-03-28",
  "status": "Released",
  "runtime": 80,
  "original_language": "es",
  "spoken_languages": [
    {
      "english_name": "Spanish",
      "iso_639_1": "es",
      "name": "Espa\u00f1ol"
    }
  ],
  "origin_country": [
    "MX"
  ],
  "genres": [
    {
      "id": 12,
      "name": "Adventure"
    },
    {
      "id": 878,
      "name": "Science Fiction"
    },
    {
      "id": 27,
      "name": "Horror"
    }
  ]
}