{
  "id": 1098378,
  "title": "Your Monster",
  "original_title": "Your Monster",
  "release_date": "2024-10-25",
  "status": "Released",
  "runtime": 104,
  "original_language": "en",
  "spoken_languages": [
    {
      "english_name": "English",
      "iso_639_1": "en",
      "name": "English"
    }
  ],
  "origin_country": [
    "US"
  ],
  "genres": [
    {
      "id": 10749,
      "name": "Romance"
    },
    {
      "id": 35,
      "name": "Comedy"
    },
    {
      "id": 27,
      "name": "Horror"
    }
  ]
}