{
  "id": 60142,
  "title": "Master, a Building in Copacabana",
  "original_title": "Edif\u00edcio Master",
  "release_date": "2002-11-22",
  "status": "Released",
  "runtime": 110,
  "original_language": "pt",
  "spoken_languages": [
    {
      "english_name": "English",
      "iso_639_1": "en",
      "name": "English"
    },
    {
      "english_name": "Portuguese",
      "iso_639_1": "pt",
      "name": "Portugu\u00eas"
    }
  ],
  "origin_country": [
    "BR"
  ],
  "genres": [
    {
      "id": 99,
      "name": "Documentary"
    }
  ]
}