{
  "id": 497370,
  "title": "The Drug King",
  "original_title": "\ub9c8\uc57d\uc655",
  "release_date": "2018-12-19",
  "status": "Released",
  "runtime": 139,
  "original_language": "ko",
  "spoken_languages": [
    {
      "english_name": "English",
      "iso_639_1": "en",
      "name": "English"
    },
    {
      "english_name": "Korean",
      "iso_639_1": "ko",
      "name": "\ud55c\uad6d\uc5b4/\uc870\uc120\ub9d0"
    },
    {
      "english_name": "Portuguese",
      "iso_639_1": "pt",
      "name": "Portugu\u00eas"
    },
    {
      "english_name": "Japanese",
      "iso_639_1": "ja",
      "name": "\u65e5\u672c\u8a9e"
    }
  ],
  "origin_country": [
    "KR"
  ],
  "genres": [
    {
      "id": 80,
      "name": "Crime"
    },
    {
      "id": 28,
      "name": "Action"
    },
    {
      "id": 18,
      "name": "Drama"
    }
  ]
}