{
  "id": 1410189,
  "title": "Kontinental '25",
  "original_title": "Kontinental '25",
  "release_date": "2025-09-24",
  "status": "Released",
  "runtime": 109,
  "original_language": "ro",
  "spoken_languages": [
    {
      "english_name": "Hungarian",
      "iso_639_1": "hu",
      "name": "Magyar"
    },
    {
      "english_name": "German",
      "iso_639_1": "de",
      "name": "Deutsch"
    },
    {
      "english_name": "Latin",
      "iso_639_1": "la",
      "name": "Latin"
    },
    {
      "english_name": "Romanian",
      "iso_639_1": "ro",
      "name": "Rom\u00e2n\u0103"
    },
    {
      "english_name": "English",
      "iso_639_1": "en",
      "name": "English"
    }
  ],
  "origin_country": [
    "RO"
  ],
  "genres": [
    {
      "id": 35,
      "name": "Comedy"
    },
    {
      "id": 18,
      "name": "Drama"
    }
  ]
}