{
  "id": 1499,
  "title": "Teenage Mutant Ninja Turtles III",
  "original_title": "Teenage Mutant Ninja Turtles III",
  "release_date": "1993-03-17",
  "status": "Released",
  "runtime": 95,
  "original_language": "en",
  "spoken_languages": [
    {
      "english_name": "English",
      "iso_639_1": "en",
      "name": "English"
    }
  ],
  "origin_country": [
    "US",
    "HK"
  ],
  "genres": [
    {
      "id": 28,
      "name": "Action"
    },
    {
      "id": 12,
      "name": "Adventure"
    },
    {
      "id": 35,
      "name": "Comedy"
    },
    {
      "id": 10751,
      "name": "Family"
    },
    {
      "id": 14,
      "name": "Fantasy"
    },
    {
      "id": 878,
      "name": "Science Fiction"
    }
  ]
}