{
  "id": 332169,
  "title": "Persona 3 the Movie: #3 Falling Down",
  "original_title": "PERSONA3 THE MOVIE \u2014#3 Falling Down\u2014",
  "release_date": "2015-04-04",
  "status": "Released",
  "runtime": 87,
  "original_language": "ja",
  "spoken_languages": [
    {
      "english_name": "Japanese",
      "iso_639_1": "ja",
      "name": "\u65e5\u672c\u8a9e"
    }
  ],
  "origin_country": [
    "JP"
  ],
  "genres": [
    {
      "id": 12,
      "name": "Adventure"
    },
    {
      "id": 28,
      "name": "Action"
    },
    {
      "id": 16,
      "name": "Animation"
    },
    {
      "id": 18,
      "name": "Drama"
    },
    {
      "id": 14,
      "name": "Fantasy"
    },
    {
      "id": 878,
      "name": "Science Fiction"
    }
  ]
}