{
  "id": 463633,
  "title": "Journey from Greece",
  "original_title": "Djam",
  "release_date": "2017-08-09",
  "status": "Released",
  "runtime": 97,
  "original_language": "fr",
  "spoken_languages": [
    {
      "english_name": "Turkish",
      "iso_639_1": "tr",
      "name": "T\u00fcrk\u00e7e"
    },
    {
      "english_name": "French",
      "iso_639_1": "fr",
      "name": "Fran\u00e7ais"
    },
    {
      "english_name": "Greek",
      "iso_639_1": "el",
      "name": "\u03b5\u03bb\u03bb\u03b7\u03bd\u03b9\u03ba\u03ac"
    },
    {
      "english_name": "English",
      "iso_639_1": "en",
      "name": "English"
    }
  ],
  "origin_country": [
    "FR"
  ],
  "genres": [
    {
      "id": 18,
      "name": "Drama"
    },
    {
      "id": 10402,
      "name": "Music"
    }
  ]
}