{
  "id": 164,
  "title": "Breakfast at Tiffany's",
  "original_title": "Breakfast at Tiffany's",
  "release_date": "1961-10-06",
  "status": "Released",
  "runtime": 115,
  "original_language": "en",
  "spoken_languages": [
    {
      "english_name": "English",
      "iso_639_1": "en",
      "name": "English"
    },
    {
      "english_name": "Portuguese",
      "iso_639_1": "pt",
      "name": "Portugu\u00eas"
    }
  ],
  "origin_country": [
    "US"
  ],
  "genres": [
    {
      "id": 35,
      "name": "Comedy"
    },
    {
      "id": 10749,
      "name": "Romance"
    },
    {
      "id": 18,
      "name": "Drama"
    }
  ]
}