{
  "id": 16990,
  "title": "Escaflowne: The Movie",
  "original_title": "\u30a8\u30b9\u30ab\u30d5\u30ed\u30fc\u30cd",
  "release_date": "2000-06-24",
  "status": "Released",
  "runtime": 98,
  "original_language": "ja",
  "spoken_languages": [
    {
      "english_name": "Japanese",
      "iso_639_1": "ja",
      "name": "\u65e5\u672c\u8a9e"
    }
  ],
  "origin_country": [
    "JP"
  ],
  "genres": [
    {
      "id": 16,
      "name": "Animation"
    },
    {
      "id": 12,
      "name": "Adventure"
    },
    {
      "id": 18,
      "name": "Drama"
    },
    {
      "id": 14,
      "name": "Fantasy"
    }
  ]
}