{
  "id": 530079,
  "title": "Ride Your Wave",
  "original_title": "\u304d\u307f\u3068\u3001\u6ce2\u306b\u306e\u308c\u305f\u3089",
  "release_date": "2019-06-21",
  "status": "Released",
  "runtime": 96,
  "original_language": "ja",
  "spoken_languages": [
    {
      "english_name": "Japanese",
      "iso_639_1": "ja",
      "name": "\u65e5\u672c\u8a9e"
    }
  ],
  "origin_country": [
    "JP"
  ],
  "genres": [
    {
      "id": 16,
      "name": "Animation"
    },
    {
      "id": 10749,
      "name": "Romance"
    },
    {
      "id": 35,
      "name": "Comedy"
    },
    {
      "id": 18,
      "name": "Drama"
    },
    {
      "id": 14,
      "name": "Fantasy"
    }
  ]
}