{
  "id": 538002,
  "title": "They'll Love Me When I'm Dead",
  "original_title": "They'll Love Me When I'm Dead",
  "release_date": "2018-08-31",
  "status": "Released",
  "runtime": 98,
  "original_language": "en",
  "spoken_languages": [
    {
      "english_name": "Croatian",
      "iso_639_1": "hr",
      "name": "Hrvatski"
    },
    {
      "english_name": "French",
      "iso_639_1": "fr",
      "name": "Fran\u00e7ais"
    },
    {
      "english_name": "English",
      "iso_639_1": "en",
      "name": "English"
    }
  ],
  "origin_country": [
    "US"
  ],
  "genres": [
    {
      "id": 99,
      "name": "Documentary"
    }
  ]
}