{
  "id": 40461,
  "title": "\u00c6nigma",
  "original_title": "\u00c6nigma",
  "release_date": "1987-12-30",
  "status": "Released",
  "runtime": 90,
  "original_language": "it",
  "spoken_languages": [
    {
      "english_name": "English",
      "iso_639_1": "en",
      "name": "English"
    },
    {
      "english_name": "Italian",
      "iso_639_1": "it",
      "name": "Italiano"
    }
  ],
  "origin_country": [
    "IT"
  ],
  "genres": [
    {
      "id": 27,
      "name": "Horror"
    }
  ]
}