{
  "id": 408,
  "title": "Snow White and the Seven Dwarfs",
  "original_title": "Snow White and the Seven Dwarfs",
  "release_date": "1938-01-14",
  "status": "Released",
  "runtime": 83,
  "original_language": "en",
  "spoken_languages": [
    {
      "english_name": "English",
      "iso_639_1": "en",
      "name": "English"
    }
  ],
  "origin_country": [
    "US"
  ],
  "genres": [
    {
      "id": 14,
      "name": "Fantasy"
    },
    {
      "id": 16,
      "name": "Animation"
    },
    {
      "id": 10751,
      "name": "Family"
    }
  ]
}