{
  "id": 40823,
  "title": "The Man Who Copied",
  "original_title": "O Homem Que Copiava",
  "release_date": "2003-06-13",
  "status": "Released",
  "runtime": 123,
  "original_language": "pt",
  "spoken_languages": [
    {
      "english_name": "Portuguese",
      "iso_639_1": "pt",
      "name": "Portugu\u00eas"
    }
  ],
  "origin_country": [
    "BR"
  ],
  "genres": [
    {
      "id": 35,
      "name": "Comedy"
    },
    {
      "id": 18,
      "name": "Drama"
    },
    {
      "id": 10749,
      "name": "Romance"
    },
    {
      "id": 80,
      "name": "Crime"
    }
  ]
}