{
  "id": 15716,
  "title": "The Pirates of Penzance",
  "original_title": "The Pirates of Penzance",
  "release_date": "1983-02-18",
  "status": "Released",
  "runtime": 112,
  "original_language": "en",
  "spoken_languages": [
    {
      "english_name": "English",
      "iso_639_1": "en",
      "name": "English"
    }
  ],
  "origin_country": [
    "US",
    "GB"
  ],
  "genres": [
    {
      "id": 35,
      "name": "Comedy"
    },
    {
      "id": 10402,
      "name": "Music"
    },
    {
      "id": 10749,
      "name": "Romance"
    },
    {
      "id": 12,
      "name": "Adventure"
    }
  ]
}