{
  "id": 157350,
  "title": "Divergent",
  "original_title": "Divergent",
  "release_date": "2014-03-14",
  "status": "Released",
  "runtime": 139,
  "original_language": "en",
  "spoken_languages": [
    {
      "english_name": "English",
      "iso_639_1": "en",
      "name": "English"
    }
  ],
  "origin_country": [
    "US"
  ],
  "genres": [
    {
      "id": 28,
      "name": "Action"
    },
    {
      "id": 12,
      "name": "Adventure"
    },
    {
      "id": 878,
      "name": "Science Fiction"
    }
  ]
}