{
  "id": 890771,
  "title": "The Black Demon",
  "original_title": "The Black Demon",
  "release_date": "2023-04-26",
  "status": "Released",
  "runtime": 101,
  "original_language": "en",
  "spoken_languages": [
    {
      "english_name": "English",
      "iso_639_1": "en",
      "name": "English"
    },
    {
      "english_name": "Spanish",
      "iso_639_1": "es",
      "name": "Espa\u00f1ol"
    }
  ],
  "origin_country": [
    "US"
  ],
  "genres": [
    {
      "id": 53,
      "name": "Thriller"
    },
    {
      "id": 27,
      "name": "Horror"
    }
  ]
}