{
  "id": 1212855,
  "title": "Fight or Flight",
  "original_title": "Fight or Flight",
  "release_date": "2025-04-03",
  "status": "Released",
  "runtime": 101,
  "original_language": "en",
  "spoken_languages": [
    {
      "english_name": "English",
      "iso_639_1": "en",
      "name": "English"
    }
  ],
  "origin_country": [
    "US",
    "GB"
  ],
  "genres": [
    {
      "id": 28,
      "name": "Action"
    },
    {
      "id": 35,
      "name": "Comedy"
    },
    {
      "id": 53,
      "name": "Thriller"
    }
  ]
}