{
  "id": 1224666,
  "title": "They Will Be Dust",
  "original_title": "Polvo ser\u00e1n",
  "release_date": "2024-11-15",
  "status": "Released",
  "runtime": 106,
  "original_language": "es",
  "spoken_languages": [
    {
      "english_name": "English",
      "iso_639_1": "en",
      "name": "English"
    },
    {
      "english_name": "Spanish",
      "iso_639_1": "es",
      "name": "Espa\u00f1ol"
    }
  ],
  "origin_country": [
    "IT",
    "ES",
    "CH"
  ],
  "genres": [
    {
      "id": 18,
      "name": "Drama"
    },
    {
      "id": 10402,
      "name": "Music"
    },
    {
      "id": 35,
      "name": "Comedy"
    }
  ]
}