{
  "id": 1232732,
  "title": "Quite Like Paradise",
  "original_title": "Casi el Para\u00edso",
  "release_date": "2024-09-12",
  "status": "Released",
  "runtime": 120,
  "original_language": "es",
  "spoken_languages": [
    {
      "english_name": "Italian",
      "iso_639_1": "it",
      "name": "Italiano"
    },
    {
      "english_name": "English",
      "iso_639_1": "en",
      "name": "English"
    },
    {
      "english_name": "Spanish",
      "iso_639_1": "es",
      "name": "Espa\u00f1ol"
    }
  ],
  "origin_country": [
    "MX",
    "IT"
  ],
  "genres": [
    {
      "id": 18,
      "name": "Drama"
    },
    {
      "id": 80,
      "name": "Crime"
    },
    {
      "id": 35,
      "name": "Comedy"
    }
  ]
}