{
  "id": 1252037,
  "title": "The Tank",
  "original_title": "Der Tiger",
  "release_date": "2025-09-18",
  "status": "Released",
  "runtime": 117,
  "original_language": "de",
  "spoken_languages": [
    {
      "english_name": "German",
      "iso_639_1": "de",
      "name": "Deutsch"
    }
  ],
  "origin_country": [
    "DE"
  ],
  "genres": [
    {
      "id": 10752,
      "name": "War"
    },
    {
      "id": 28,
      "name": "Action"
    },
    {
      "id": 18,
      "name": "Drama"
    }
  ]
}