{
  "id": 12539,
  "title": "The Black Tulip",
  "original_title": "La Tulipe noire",
  "release_date": "1964-02-28",
  "status": "Released",
  "runtime": 115,
  "original_language": "fr",
  "spoken_languages": [
    {
      "english_name": "French",
      "iso_639_1": "fr",
      "name": "Fran\u00e7ais"
    },
    {
      "english_name": "Italian",
      "iso_639_1": "it",
      "name": "Italiano"
    }
  ],
  "origin_country": [
    "FR"
  ],
  "genres": [
    {
      "id": 12,
      "name": "Adventure"
    }
  ]
}